[["Map",1,2,9,10],"meta::meta",["Map",3,4,5,6,7,8],"astro-version","5.14.8","content-config-digest","cec3e75bd5e39fe1","astro-config-digest","{\"root\":{},\"srcDir\":{},\"publicDir\":{},\"outDir\":{},\"cacheDir\":{},\"site\":\"https://blog.fabform.io\",\"compressHTML\":true,\"base\":\"/\",\"trailingSlash\":\"ignore\",\"output\":\"static\",\"scopedStyleStrategy\":\"attribute\",\"build\":{\"format\":\"directory\",\"client\":{},\"server\":{},\"assets\":\"_astro\",\"serverEntry\":\"entry.mjs\",\"redirects\":true,\"inlineStylesheets\":\"auto\",\"concurrency\":1},\"server\":{\"open\":false,\"host\":false,\"port\":4321,\"streaming\":true,\"allowedHosts\":[]},\"redirects\":{},\"image\":{\"endpoint\":{\"route\":\"/_image\"},\"service\":{\"entrypoint\":\"astro/assets/services/sharp\",\"config\":{}},\"domains\":[],\"remotePatterns\":[],\"responsiveStyles\":false},\"devToolbar\":{\"enabled\":true},\"markdown\":{\"syntaxHighlight\":{\"type\":\"shiki\",\"excludeLangs\":[\"math\"]},\"shikiConfig\":{\"langs\":[],\"langAlias\":{},\"theme\":\"poimandres\",\"themes\":{},\"wrap\":false,\"transformers\":[]},\"remarkPlugins\":[],\"rehypePlugins\":[],\"remarkRehype\":{},\"gfm\":true,\"smartypants\":true},\"security\":{\"checkOrigin\":true,\"allowedDomains\":[]},\"env\":{\"schema\":{},\"validateSecrets\":false},\"experimental\":{\"clientPrerender\":false,\"contentIntellisense\":false,\"headingIdCompat\":false,\"preserveScriptOrder\":false,\"liveContentCollections\":false,\"csp\":false,\"staticImportMetaEnv\":false,\"chromeDevtoolsWorkspace\":false,\"failOnPrerenderConflict\":false},\"legacy\":{\"collections\":false}}","posts",["Map",11,12,78,79,168,169,208,209],"food-packaging-customer-service-numbers-decline",{"id":11,"data":13,"body":29,"filePath":30,"assetImports":31,"digest":33,"rendered":34,"legacyId":77},{"title":14,"pubDate":15,"description":16,"team":17,"image":18,"tags":21},"Why Food Brands Are Moving Away from Customer Service Numbers on Packaging",["Date","2025-10-23T00:00:00.000Z"],"Explore why food manufacturers are removing customer service numbers from packaging and replacing them with QR code feedback forms powered by FabForm.io.","fabform-core",{"url":19,"alt":20},"__ASTRO_IMAGE_/src/images/blog/2.jpg","Food label with QR code replacing customer service number",[22,23,24,25,26,27,28],"food packaging","consumer feedback","QR code","customer service","FabForm.io","form builder","CPG trends","**Food brands are removing customer service numbers from packaging to reduce costs, streamline support, and shift consumers toward digital feedback channels like QR code forms.** This change reflects broader trends in mobile-first engagement, automation, and real-time analytics.\n\n---\n\n## Why Customer Service Numbers Are Disappearing from Food Packaging\n\n### 1. **Low Usage and ROI**\nMost consumers rarely call customer service numbers printed on packaging. A Reddit thread confirms that calls are infrequent and often driven by unusual circumstances like mislabeled products. Maintaining phone support for such low engagement is costly and inefficient.\n\n### 2. **Cost Reduction**\nBrands are quietly eliminating phone numbers, live chat, and direct email support to cut operational costs. This shift outsources problem-solving to consumers via self-service tools like FAQ pages and AI chatbots. Removing phone support reduces staffing needs and infrastructure expenses.\n\n### 3. **Shift to Digital Feedback**\nModern consumers prefer mobile-first, asynchronous communication. QR codes on packaging link directly to feedback forms, allowing brands to collect structured data without human intervention. This method is faster, cheaper, and more scalable than phone support.\n\n### 4. **Real-Time Analytics**\nPhone calls offer anecdotal feedback with no easy way to quantify or segment responses. QR code forms—especially those built with tools like FabForm.io—enable:\n\n- Timestamped responses\n- Product-specific feedback\n- Exportable datasets\n- Integration with CRM and analytics platforms\n\n### 5. **Better UX for Consumers**\nCalling a support line involves wait times, IVR menus, and potential frustration. In contrast, scanning a QR code and answering one question at a time is intuitive, fast, and mobile-optimized. This improves the overall customer experience and increases feedback volume.\n\n### 6. **Packaging Space Optimization**\nRemoving phone numbers frees up label space for more relevant content: QR codes, nutritional info, sustainability messaging, or promotional CTAs. Brands can use packaging real estate more strategically.\n\n---\n\n## What Food Brands Are Doing Instead\n\n- **Embedding QR codes** linked to branded feedback forms\n- **Using dynamic QR codes** to update form links without reprinting packaging\n- **Offering incentives** (e.g., coupons) for completed feedback\n- **Integrating feedback into product development cycles**\n\n---\n\n## SEO Keywords Targeted\n\nThis article is optimized for search terms like:\n\n- why food brands removed customer service numbers\n- QR code feedback on food packaging\n- modern feedback tools for packaged goods\n- FabForm.io feedback forms\n- mobile-first consumer feedback strategy\n- replacing phone support with QR codes\n\n---\n\n## Conclusion\n\nFood brands are moving away from customer service numbers on packaging because they’re outdated, expensive, and underused. QR code feedback forms offer a modern, scalable alternative that aligns with consumer behavior and brand goals. Tools like FabForm.io make it easy to implement mobile-first feedback systems that deliver real-time insights and better customer experiences.","src/content/posts/food-packaging-customer-service-numbers-decline.md",[32],"/src/images/blog/2.jpg","d3c587806dc8ac2a",{"html":35,"metadata":36},"\u003Cp>\u003Cstrong>Food brands are removing customer service numbers from packaging to reduce costs, streamline support, and shift consumers toward digital feedback channels like QR code forms.\u003C/strong> This change reflects broader trends in mobile-first engagement, automation, and real-time analytics.\u003C/p>\n\u003Chr>\n\u003Ch2 id=\"why-customer-service-numbers-are-disappearing-from-food-packaging\">Why Customer Service Numbers Are Disappearing from Food Packaging\u003C/h2>\n\u003Ch3 id=\"1-low-usage-and-roi\">1. \u003Cstrong>Low Usage and ROI\u003C/strong>\u003C/h3>\n\u003Cp>Most consumers rarely call customer service numbers printed on packaging. A Reddit thread confirms that calls are infrequent and often driven by unusual circumstances like mislabeled products. Maintaining phone support for such low engagement is costly and inefficient.\u003C/p>\n\u003Ch3 id=\"2-cost-reduction\">2. \u003Cstrong>Cost Reduction\u003C/strong>\u003C/h3>\n\u003Cp>Brands are quietly eliminating phone numbers, live chat, and direct email support to cut operational costs. This shift outsources problem-solving to consumers via self-service tools like FAQ pages and AI chatbots. Removing phone support reduces staffing needs and infrastructure expenses.\u003C/p>\n\u003Ch3 id=\"3-shift-to-digital-feedback\">3. \u003Cstrong>Shift to Digital Feedback\u003C/strong>\u003C/h3>\n\u003Cp>Modern consumers prefer mobile-first, asynchronous communication. QR codes on packaging link directly to feedback forms, allowing brands to collect structured data without human intervention. This method is faster, cheaper, and more scalable than phone support.\u003C/p>\n\u003Ch3 id=\"4-real-time-analytics\">4. \u003Cstrong>Real-Time Analytics\u003C/strong>\u003C/h3>\n\u003Cp>Phone calls offer anecdotal feedback with no easy way to quantify or segment responses. QR code forms—especially those built with tools like FabForm.io—enable:\u003C/p>\n\u003Cul>\n\u003Cli>Timestamped responses\u003C/li>\n\u003Cli>Product-specific feedback\u003C/li>\n\u003Cli>Exportable datasets\u003C/li>\n\u003Cli>Integration with CRM and analytics platforms\u003C/li>\n\u003C/ul>\n\u003Ch3 id=\"5-better-ux-for-consumers\">5. \u003Cstrong>Better UX for Consumers\u003C/strong>\u003C/h3>\n\u003Cp>Calling a support line involves wait times, IVR menus, and potential frustration. In contrast, scanning a QR code and answering one question at a time is intuitive, fast, and mobile-optimized. This improves the overall customer experience and increases feedback volume.\u003C/p>\n\u003Ch3 id=\"6-packaging-space-optimization\">6. \u003Cstrong>Packaging Space Optimization\u003C/strong>\u003C/h3>\n\u003Cp>Removing phone numbers frees up label space for more relevant content: QR codes, nutritional info, sustainability messaging, or promotional CTAs. Brands can use packaging real estate more strategically.\u003C/p>\n\u003Chr>\n\u003Ch2 id=\"what-food-brands-are-doing-instead\">What Food Brands Are Doing Instead\u003C/h2>\n\u003Cul>\n\u003Cli>\u003Cstrong>Embedding QR codes\u003C/strong> linked to branded feedback forms\u003C/li>\n\u003Cli>\u003Cstrong>Using dynamic QR codes\u003C/strong> to update form links without reprinting packaging\u003C/li>\n\u003Cli>\u003Cstrong>Offering incentives\u003C/strong> (e.g., coupons) for completed feedback\u003C/li>\n\u003Cli>\u003Cstrong>Integrating feedback into product development cycles\u003C/strong>\u003C/li>\n\u003C/ul>\n\u003Chr>\n\u003Ch2 id=\"seo-keywords-targeted\">SEO Keywords Targeted\u003C/h2>\n\u003Cp>This article is optimized for search terms like:\u003C/p>\n\u003Cul>\n\u003Cli>why food brands removed customer service numbers\u003C/li>\n\u003Cli>QR code feedback on food packaging\u003C/li>\n\u003Cli>modern feedback tools for packaged goods\u003C/li>\n\u003Cli>FabForm.io feedback forms\u003C/li>\n\u003Cli>mobile-first consumer feedback strategy\u003C/li>\n\u003Cli>replacing phone support with QR codes\u003C/li>\n\u003C/ul>\n\u003Chr>\n\u003Ch2 id=\"conclusion\">Conclusion\u003C/h2>\n\u003Cp>Food brands are moving away from customer service numbers on packaging because they’re outdated, expensive, and underused. QR code feedback forms offer a modern, scalable alternative that aligns with consumer behavior and brand goals. Tools like FabForm.io make it easy to implement mobile-first feedback systems that deliver real-time insights and better customer experiences.\u003C/p>",{"headings":37,"localImagePaths":70,"remoteImagePaths":71,"frontmatter":72,"imagePaths":76},[38,42,46,49,52,55,58,61,64,67],{"depth":39,"slug":40,"text":41},2,"why-customer-service-numbers-are-disappearing-from-food-packaging","Why Customer Service Numbers Are Disappearing from Food Packaging",{"depth":43,"slug":44,"text":45},3,"1-low-usage-and-roi","1. Low Usage and ROI",{"depth":43,"slug":47,"text":48},"2-cost-reduction","2. Cost Reduction",{"depth":43,"slug":50,"text":51},"3-shift-to-digital-feedback","3. Shift to Digital Feedback",{"depth":43,"slug":53,"text":54},"4-real-time-analytics","4. Real-Time Analytics",{"depth":43,"slug":56,"text":57},"5-better-ux-for-consumers","5. Better UX for Consumers",{"depth":43,"slug":59,"text":60},"6-packaging-space-optimization","6. Packaging Space Optimization",{"depth":39,"slug":62,"text":63},"what-food-brands-are-doing-instead","What Food Brands Are Doing Instead",{"depth":39,"slug":65,"text":66},"seo-keywords-targeted","SEO Keywords Targeted",{"depth":39,"slug":68,"text":69},"conclusion","Conclusion",[],[],{"pubDate":73,"team":17,"title":14,"description":16,"image":74,"tags":75},["Date","2025-10-23T00:00:00.000Z"],{"url":32,"alt":20},[22,23,24,25,26,27,28],[],"food-packaging-customer-service-numbers-decline.md","qr-code-feedback-food-packaging",{"id":78,"data":80,"body":89,"filePath":90,"assetImports":91,"digest":93,"rendered":94,"legacyId":167},{"title":81,"pubDate":82,"description":83,"team":17,"image":84,"tags":87},"QR Code Feedback on Food Packaging: A Modern Approach to Consumer Insights",["Date","2025-10-23T00:00:00.000Z"],"Learn how food brands can use QR codes and one-question-at-a-time forms to collect fast, structured consumer feedback directly from product labels—powered by FabForm.io.",{"url":85,"alt":86},"__ASTRO_IMAGE_/src/images/blog/1.jpg","Food packaging with a QR code and mobile feedback form",[22,23,24,27,26,88],"Typeform alternative","# How to Collect Consumer Feedback Using QR Codes on Food Packaging\r\n\r\n## Introduction: Why Feedback Matters in Packaged Food\r\n\r\nIn the competitive world of packaged food, understanding consumer preferences is critical for product improvement, brand loyalty, and market differentiation. Traditional feedback channels—such as mailing addresses printed on labels or customer service phone numbers—are slow, inefficient, and rarely used. Today’s consumers expect convenience, speed, and mobile-first experiences.\r\n\r\nOne of the most effective ways to meet these expectations is by embedding a **QR code directly on food packaging**, linked to a **mobile-friendly feedback form**. This article explores how food brands can use FabForm.io’s Typeform-style form builder to collect structured, actionable feedback—one question at a time—through QR code scanning.\r\n\r\n---\r\n\r\n## What Is QR Code Feedback on Food Packaging?\r\n\r\nQR code feedback involves printing a scannable code on the product label that directs consumers to a digital form. Using FabForm.io’s built-in QR scanner, consumers can instantly access a branded feedback experience that mimics Typeform’s conversational flow. The form asks one question at a time, reducing friction and increasing completion rates.\r\n\r\nThis method is ideal for:\r\n\r\n- Packaged food manufacturers\r\n- Private-label brands\r\n- Packaging designers\r\n- Consumer research teams\r\n- Retailers seeking post-purchase insights\r\n\r\n---\r\n\r\n## Benefits of QR Code Feedback vs Traditional Methods\r\n\r\n### 1. Speed and Convenience\r\n\r\n- **QR Code**: Instant access via smartphone. No app required.\r\n- **Mailing Address**: Requires postage, envelopes, and effort.\r\n- **Customer Service Number**: Requires time, patience, and availability.\r\n\r\n### 2. Mobile Optimization\r\n\r\nFabForm.io forms are designed for mobile-first interaction. Consumers scan and respond while holding the product, often during or immediately after use—maximizing relevance and recall.\r\n\r\n### 3. Higher Engagement Rates\r\n\r\nOne-question-at-a-time forms reduce cognitive load and feel less like a survey and more like a conversation. This format increases response rates and data quality.\r\n\r\n### 4. Real-Time Analytics\r\n\r\nUnlike mail or phone feedback, QR code forms provide:\r\n\r\n- Timestamped responses\r\n- Geolocation data (if enabled)\r\n- Product-specific segmentation\r\n- Exportable datasets for analysis\r\n\r\n### 5. Cost Efficiency\r\n\r\n- No postage or call center staffing\r\n- No manual data entry\r\n- No printing of long forms\r\n\r\n---\r\n\r\n## How to Implement QR Code Feedback on Food Labels\r\n\r\n### Step 1: Design the Feedback Form\r\n\r\nUse FabForm.io’s form builder to create a branded, conversational form. Include:\r\n\r\n- Product name or batch number\r\n- One-question-at-a-time format\r\n- Optional incentive (e.g., discount code)\r\n\r\n### Step 2: Generate and Test the QR Code\r\n\r\nFabForm.io supports dynamic QR codes that can be updated without reprinting packaging. Test the code across devices and ensure it links to the correct form.\r\n\r\n### Step 3: Print the QR Code on Packaging\r\n\r\nPlace the code in a visible area with a clear call-to-action:\r\n\r\n- “Scan to share your thoughts”\r\n- “Tell us what you think”\r\n- “Quick feedback—no app needed”\r\n\r\n### Step 4: Monitor and Analyze Responses\r\n\r\nUse FabForm.io’s dashboard to track:\r\n\r\n- Scan rates\r\n- Completion rates\r\n- Common feedback themes\r\n- Product-specific insights\r\n\r\n---\r\n\r\n## SEO Keywords for Food Packaging Feedback Strategy\r\n\r\n\r\n- QR code feedback on food packaging\r\n- food label survey tools\r\n- mobile feedback forms for packaged goods\r\n- consumer feedback via QR code\r\n- Typeform alternative for food brands\r\n- FabForm.io QR scanner for packaging\r\n- one-question-at-a-time feedback form\r\n- modern feedback tools for food manufacturers\r\n- how to collect feedback from food packaging\r\n- digital survey on food label\r\n\r\n\r\n---\r\n\r\n## Use Cases and Industry Applications\r\n\r\n### Product Development\r\n\r\nQuick feedback loops help refine flavor, texture, packaging design, and shelf appeal.\r\n\r\n### Quality Control\r\n\r\nConsumers can report issues (e.g., damaged packaging, spoilage) instantly, enabling faster resolution.\r\n\r\n### Marketing and Loyalty\r\n\r\nForms can include opt-in fields for promotions, newsletters, or loyalty programs.\r\n\r\n### Regulatory Compliance\r\n\r\nStructured feedback helps identify labeling confusion, allergen concerns, or dietary claims that need clarification.\r\n\r\n---\r\n\r\n## Conclusion: Why QR Code Feedback Is the Future of Food Packaging\r\n\r\nEmbedding QR codes on food packaging linked to FabForm.io’s one-question-at-a-time feedback forms is a modern, scalable, and cost-effective way to gather consumer insights. Compared to mailing addresses and customer service numbers, this method offers:\r\n\r\n- Faster response times\r\n- Higher engagement\r\n- Better data quality\r\n- Lower operational costs\r\n\r\nFood brands that adopt QR code feedback will gain a competitive edge in responsiveness, product innovation, and customer satisfaction.","src/content/posts/qr-code-feedback-food-packaging.md",[92],"/src/images/blog/1.jpg","8c5afb7e4c8219f7",{"html":95,"metadata":96},"\u003Ch1 id=\"how-to-collect-consumer-feedback-using-qr-codes-on-food-packaging\">How to Collect Consumer Feedback Using QR Codes on Food Packaging\u003C/h1>\n\u003Ch2 id=\"introduction-why-feedback-matters-in-packaged-food\">Introduction: Why Feedback Matters in Packaged Food\u003C/h2>\n\u003Cp>In the competitive world of packaged food, understanding consumer preferences is critical for product improvement, brand loyalty, and market differentiation. Traditional feedback channels—such as mailing addresses printed on labels or customer service phone numbers—are slow, inefficient, and rarely used. Today’s consumers expect convenience, speed, and mobile-first experiences.\u003C/p>\n\u003Cp>One of the most effective ways to meet these expectations is by embedding a \u003Cstrong>QR code directly on food packaging\u003C/strong>, linked to a \u003Cstrong>mobile-friendly feedback form\u003C/strong>. This article explores how food brands can use FabForm.io’s Typeform-style form builder to collect structured, actionable feedback—one question at a time—through QR code scanning.\u003C/p>\n\u003Chr>\n\u003Ch2 id=\"what-is-qr-code-feedback-on-food-packaging\">What Is QR Code Feedback on Food Packaging?\u003C/h2>\n\u003Cp>QR code feedback involves printing a scannable code on the product label that directs consumers to a digital form. Using FabForm.io’s built-in QR scanner, consumers can instantly access a branded feedback experience that mimics Typeform’s conversational flow. The form asks one question at a time, reducing friction and increasing completion rates.\u003C/p>\n\u003Cp>This method is ideal for:\u003C/p>\n\u003Cul>\n\u003Cli>Packaged food manufacturers\u003C/li>\n\u003Cli>Private-label brands\u003C/li>\n\u003Cli>Packaging designers\u003C/li>\n\u003Cli>Consumer research teams\u003C/li>\n\u003Cli>Retailers seeking post-purchase insights\u003C/li>\n\u003C/ul>\n\u003Chr>\n\u003Ch2 id=\"benefits-of-qr-code-feedback-vs-traditional-methods\">Benefits of QR Code Feedback vs Traditional Methods\u003C/h2>\n\u003Ch3 id=\"1-speed-and-convenience\">1. Speed and Convenience\u003C/h3>\n\u003Cul>\n\u003Cli>\u003Cstrong>QR Code\u003C/strong>: Instant access via smartphone. No app required.\u003C/li>\n\u003Cli>\u003Cstrong>Mailing Address\u003C/strong>: Requires postage, envelopes, and effort.\u003C/li>\n\u003Cli>\u003Cstrong>Customer Service Number\u003C/strong>: Requires time, patience, and availability.\u003C/li>\n\u003C/ul>\n\u003Ch3 id=\"2-mobile-optimization\">2. Mobile Optimization\u003C/h3>\n\u003Cp>FabForm.io forms are designed for mobile-first interaction. Consumers scan and respond while holding the product, often during or immediately after use—maximizing relevance and recall.\u003C/p>\n\u003Ch3 id=\"3-higher-engagement-rates\">3. Higher Engagement Rates\u003C/h3>\n\u003Cp>One-question-at-a-time forms reduce cognitive load and feel less like a survey and more like a conversation. This format increases response rates and data quality.\u003C/p>\n\u003Ch3 id=\"4-real-time-analytics\">4. Real-Time Analytics\u003C/h3>\n\u003Cp>Unlike mail or phone feedback, QR code forms provide:\u003C/p>\n\u003Cul>\n\u003Cli>Timestamped responses\u003C/li>\n\u003Cli>Geolocation data (if enabled)\u003C/li>\n\u003Cli>Product-specific segmentation\u003C/li>\n\u003Cli>Exportable datasets for analysis\u003C/li>\n\u003C/ul>\n\u003Ch3 id=\"5-cost-efficiency\">5. Cost Efficiency\u003C/h3>\n\u003Cul>\n\u003Cli>No postage or call center staffing\u003C/li>\n\u003Cli>No manual data entry\u003C/li>\n\u003Cli>No printing of long forms\u003C/li>\n\u003C/ul>\n\u003Chr>\n\u003Ch2 id=\"how-to-implement-qr-code-feedback-on-food-labels\">How to Implement QR Code Feedback on Food Labels\u003C/h2>\n\u003Ch3 id=\"step-1-design-the-feedback-form\">Step 1: Design the Feedback Form\u003C/h3>\n\u003Cp>Use FabForm.io’s form builder to create a branded, conversational form. Include:\u003C/p>\n\u003Cul>\n\u003Cli>Product name or batch number\u003C/li>\n\u003Cli>One-question-at-a-time format\u003C/li>\n\u003Cli>Optional incentive (e.g., discount code)\u003C/li>\n\u003C/ul>\n\u003Ch3 id=\"step-2-generate-and-test-the-qr-code\">Step 2: Generate and Test the QR Code\u003C/h3>\n\u003Cp>FabForm.io supports dynamic QR codes that can be updated without reprinting packaging. Test the code across devices and ensure it links to the correct form.\u003C/p>\n\u003Ch3 id=\"step-3-print-the-qr-code-on-packaging\">Step 3: Print the QR Code on Packaging\u003C/h3>\n\u003Cp>Place the code in a visible area with a clear call-to-action:\u003C/p>\n\u003Cul>\n\u003Cli>“Scan to share your thoughts”\u003C/li>\n\u003Cli>“Tell us what you think”\u003C/li>\n\u003Cli>“Quick feedback—no app needed”\u003C/li>\n\u003C/ul>\n\u003Ch3 id=\"step-4-monitor-and-analyze-responses\">Step 4: Monitor and Analyze Responses\u003C/h3>\n\u003Cp>Use FabForm.io’s dashboard to track:\u003C/p>\n\u003Cul>\n\u003Cli>Scan rates\u003C/li>\n\u003Cli>Completion rates\u003C/li>\n\u003Cli>Common feedback themes\u003C/li>\n\u003Cli>Product-specific insights\u003C/li>\n\u003C/ul>\n\u003Chr>\n\u003Ch2 id=\"seo-keywords-for-food-packaging-feedback-strategy\">SEO Keywords for Food Packaging Feedback Strategy\u003C/h2>\n\u003Cul>\n\u003Cli>QR code feedback on food packaging\u003C/li>\n\u003Cli>food label survey tools\u003C/li>\n\u003Cli>mobile feedback forms for packaged goods\u003C/li>\n\u003Cli>consumer feedback via QR code\u003C/li>\n\u003Cli>Typeform alternative for food brands\u003C/li>\n\u003Cli>FabForm.io QR scanner for packaging\u003C/li>\n\u003Cli>one-question-at-a-time feedback form\u003C/li>\n\u003Cli>modern feedback tools for food manufacturers\u003C/li>\n\u003Cli>how to collect feedback from food packaging\u003C/li>\n\u003Cli>digital survey on food label\u003C/li>\n\u003C/ul>\n\u003Chr>\n\u003Ch2 id=\"use-cases-and-industry-applications\">Use Cases and Industry Applications\u003C/h2>\n\u003Ch3 id=\"product-development\">Product Development\u003C/h3>\n\u003Cp>Quick feedback loops help refine flavor, texture, packaging design, and shelf appeal.\u003C/p>\n\u003Ch3 id=\"quality-control\">Quality Control\u003C/h3>\n\u003Cp>Consumers can report issues (e.g., damaged packaging, spoilage) instantly, enabling faster resolution.\u003C/p>\n\u003Ch3 id=\"marketing-and-loyalty\">Marketing and Loyalty\u003C/h3>\n\u003Cp>Forms can include opt-in fields for promotions, newsletters, or loyalty programs.\u003C/p>\n\u003Ch3 id=\"regulatory-compliance\">Regulatory Compliance\u003C/h3>\n\u003Cp>Structured feedback helps identify labeling confusion, allergen concerns, or dietary claims that need clarification.\u003C/p>\n\u003Chr>\n\u003Ch2 id=\"conclusion-why-qr-code-feedback-is-the-future-of-food-packaging\">Conclusion: Why QR Code Feedback Is the Future of Food Packaging\u003C/h2>\n\u003Cp>Embedding QR codes on food packaging linked to FabForm.io’s one-question-at-a-time feedback forms is a modern, scalable, and cost-effective way to gather consumer insights. Compared to mailing addresses and customer service numbers, this method offers:\u003C/p>\n\u003Cul>\n\u003Cli>Faster response times\u003C/li>\n\u003Cli>Higher engagement\u003C/li>\n\u003Cli>Better data quality\u003C/li>\n\u003Cli>Lower operational costs\u003C/li>\n\u003C/ul>\n\u003Cp>Food brands that adopt QR code feedback will gain a competitive edge in responsiveness, product innovation, and customer satisfaction.\u003C/p>",{"headings":97,"localImagePaths":160,"remoteImagePaths":161,"frontmatter":162,"imagePaths":166},[98,102,105,108,111,114,117,120,121,124,127,130,133,136,139,142,145,148,151,154,157],{"depth":99,"slug":100,"text":101},1,"how-to-collect-consumer-feedback-using-qr-codes-on-food-packaging","How to Collect Consumer Feedback Using QR Codes on Food Packaging",{"depth":39,"slug":103,"text":104},"introduction-why-feedback-matters-in-packaged-food","Introduction: Why Feedback Matters in Packaged Food",{"depth":39,"slug":106,"text":107},"what-is-qr-code-feedback-on-food-packaging","What Is QR Code Feedback on Food Packaging?",{"depth":39,"slug":109,"text":110},"benefits-of-qr-code-feedback-vs-traditional-methods","Benefits of QR Code Feedback vs Traditional Methods",{"depth":43,"slug":112,"text":113},"1-speed-and-convenience","1. Speed and Convenience",{"depth":43,"slug":115,"text":116},"2-mobile-optimization","2. Mobile Optimization",{"depth":43,"slug":118,"text":119},"3-higher-engagement-rates","3. Higher Engagement Rates",{"depth":43,"slug":53,"text":54},{"depth":43,"slug":122,"text":123},"5-cost-efficiency","5. Cost Efficiency",{"depth":39,"slug":125,"text":126},"how-to-implement-qr-code-feedback-on-food-labels","How to Implement QR Code Feedback on Food Labels",{"depth":43,"slug":128,"text":129},"step-1-design-the-feedback-form","Step 1: Design the Feedback Form",{"depth":43,"slug":131,"text":132},"step-2-generate-and-test-the-qr-code","Step 2: Generate and Test the QR Code",{"depth":43,"slug":134,"text":135},"step-3-print-the-qr-code-on-packaging","Step 3: Print the QR Code on Packaging",{"depth":43,"slug":137,"text":138},"step-4-monitor-and-analyze-responses","Step 4: Monitor and Analyze Responses",{"depth":39,"slug":140,"text":141},"seo-keywords-for-food-packaging-feedback-strategy","SEO Keywords for Food Packaging Feedback Strategy",{"depth":39,"slug":143,"text":144},"use-cases-and-industry-applications","Use Cases and Industry Applications",{"depth":43,"slug":146,"text":147},"product-development","Product Development",{"depth":43,"slug":149,"text":150},"quality-control","Quality Control",{"depth":43,"slug":152,"text":153},"marketing-and-loyalty","Marketing and Loyalty",{"depth":43,"slug":155,"text":156},"regulatory-compliance","Regulatory Compliance",{"depth":39,"slug":158,"text":159},"conclusion-why-qr-code-feedback-is-the-future-of-food-packaging","Conclusion: Why QR Code Feedback Is the Future of Food Packaging",[],[],{"pubDate":163,"team":17,"title":81,"description":83,"image":164,"tags":165},["Date","2025-10-23T00:00:00.000Z"],{"url":92,"alt":86},[22,23,24,27,26,88],[],"qr-code-feedback-food-packaging.md","typeform-alternative-fabform-99-dollar-one-time",{"id":168,"data":170,"body":174,"filePath":175,"assetImports":176,"digest":177,"rendered":178,"legacyId":207},{"title":81,"pubDate":171,"description":83,"team":17,"image":172,"tags":173},["Date","2025-10-23T00:00:00.000Z"],{"url":85,"alt":86},[22,23,24,27,26,88],"# FabForm.io: A Smarter Typeform Alternative with Better UX and No Recurring Costs\r\n\r\nIf you’re a digital marketer, growth lead, or small business owner tired of Typeform’s rising costs and slow load times, FabForm.io is the **Typeform alternative** you’ve been waiting for. It delivers the same beautiful, one-question-at-a-time experience — but faster, simpler, and with a one-time $99 price tag.\r\n\r\n## Why Marketers Are Switching to FabForm.io\r\n\r\nTypeform helped popularize conversational forms. But over time, it’s become bloated, expensive, and frustrating to manage. FabForm.io brings the same sleek UX — without the baggage.\r\n\r\n- **One-time payment of $99** — no monthly fees, no usage caps  \r\n- **Faster load times** — fewer drop-offs, more completions  \r\n- **Cleaner UX** — no distractions, just focused questions  \r\n- **Easy to embed anywhere** — websites, landing pages, email campaigns  \r\n- **Works with your tools** — Zapier, email notifications, and more  \r\n\r\n## Feature Comparison: FabForm.io vs Typeform\r\n\r\n| Feature                        | Typeform         | FabForm.io       |\r\n|-------------------------------|------------------|------------------|\r\n| One-question-at-a-time UX     | ✅                | ✅                |\r\n| Conditional logic             | ✅                | ✅                |\r\n| Custom branding               | ✅                | ✅                |\r\n| Embed in landing pages        | ✅                | ✅                |\r\n| Email notifications           | ✅                | ✅                |\r\n| Zapier integration            | ✅                | ✅                |\r\n| Load speed                    | ⚠️ Often slow     | ✅ Lightning-fast |\r\n| Pricing                       | ❌ Starts at $25/month | ✅ **$99 once, forever** |\r\n\r\nFabForm.io gives you everything you need to launch high-converting forms — without locking you into a subscription.\r\n\r\n## Built for People Who Just Want It to Work\r\n\r\nYou don’t need to be a developer. You don’t need to fiddle with code. FabForm.io is built for:\r\n\r\n- **Marketers** running lead gen campaigns  \r\n- **Agencies** building forms for clients  \r\n- **Small teams** collecting feedback, signups, or surveys  \r\n- **Anyone** who wants a clean, modern form without the monthly bill  \r\n\r\n## No Subscriptions. No Upsells. Just $99.\r\n\r\nTypeform’s pricing starts at $25/month and climbs fast. FabForm.io keeps it simple:\r\n\r\n- **One-time payment of $99**  \r\n- No recurring fees  \r\n- No usage limits  \r\n- No surprises  \r\n\r\nYou pay once. You own it. That’s it.\r\n\r\n## Try FabForm.io Today\r\n\r\nIf you’re ready to switch, FabForm.io makes it easy. Build your form, customize your branding, and go live in minutes — all for a flat $99.\r\n\r\n👉 [Start building with FabForm.io](https://fabform.io)\r\n\r\n---","src/content/posts/typeform-alternative-fabform-99-dollar-one-time.md",[92],"21724212f524ff34",{"html":179,"metadata":180},"\u003Ch1 id=\"fabformio-a-smarter-typeform-alternative-with-better-ux-and-no-recurring-costs\">FabForm.io: A Smarter Typeform Alternative with Better UX and No Recurring Costs\u003C/h1>\n\u003Cp>If you’re a digital marketer, growth lead, or small business owner tired of Typeform’s rising costs and slow load times, FabForm.io is the \u003Cstrong>Typeform alternative\u003C/strong> you’ve been waiting for. It delivers the same beautiful, one-question-at-a-time experience — but faster, simpler, and with a one-time $99 price tag.\u003C/p>\n\u003Ch2 id=\"why-marketers-are-switching-to-fabformio\">Why Marketers Are Switching to FabForm.io\u003C/h2>\n\u003Cp>Typeform helped popularize conversational forms. But over time, it’s become bloated, expensive, and frustrating to manage. FabForm.io brings the same sleek UX — without the baggage.\u003C/p>\n\u003Cul>\n\u003Cli>\u003Cstrong>One-time payment of $99\u003C/strong> — no monthly fees, no usage caps\u003C/li>\n\u003Cli>\u003Cstrong>Faster load times\u003C/strong> — fewer drop-offs, more completions\u003C/li>\n\u003Cli>\u003Cstrong>Cleaner UX\u003C/strong> — no distractions, just focused questions\u003C/li>\n\u003Cli>\u003Cstrong>Easy to embed anywhere\u003C/strong> — websites, landing pages, email campaigns\u003C/li>\n\u003Cli>\u003Cstrong>Works with your tools\u003C/strong> — Zapier, email notifications, and more\u003C/li>\n\u003C/ul>\n\u003Ch2 id=\"feature-comparison-fabformio-vs-typeform\">Feature Comparison: FabForm.io vs Typeform\u003C/h2>\n\n\n\n\n\n\n\n\n\n\n\n\n\n\n\n\n\n\n\n\n\n\n\n\n\n\n\n\n\n\n\n\n\n\n\n\n\n\n\n\n\n\n\n\n\n\n\n\n\n\n\u003Ctable>\u003Cthead>\u003Ctr>\u003Cth>Feature\u003C/th>\u003Cth>Typeform\u003C/th>\u003Cth>FabForm.io\u003C/th>\u003C/tr>\u003C/thead>\u003Ctbody>\u003Ctr>\u003Ctd>One-question-at-a-time UX\u003C/td>\u003Ctd>✅\u003C/td>\u003Ctd>✅\u003C/td>\u003C/tr>\u003Ctr>\u003Ctd>Conditional logic\u003C/td>\u003Ctd>✅\u003C/td>\u003Ctd>✅\u003C/td>\u003C/tr>\u003Ctr>\u003Ctd>Custom branding\u003C/td>\u003Ctd>✅\u003C/td>\u003Ctd>✅\u003C/td>\u003C/tr>\u003Ctr>\u003Ctd>Embed in landing pages\u003C/td>\u003Ctd>✅\u003C/td>\u003Ctd>✅\u003C/td>\u003C/tr>\u003Ctr>\u003Ctd>Email notifications\u003C/td>\u003Ctd>✅\u003C/td>\u003Ctd>✅\u003C/td>\u003C/tr>\u003Ctr>\u003Ctd>Zapier integration\u003C/td>\u003Ctd>✅\u003C/td>\u003Ctd>✅\u003C/td>\u003C/tr>\u003Ctr>\u003Ctd>Load speed\u003C/td>\u003Ctd>⚠️ Often slow\u003C/td>\u003Ctd>✅ Lightning-fast\u003C/td>\u003C/tr>\u003Ctr>\u003Ctd>Pricing\u003C/td>\u003Ctd>❌ Starts at $25/month\u003C/td>\u003Ctd>✅ \u003Cstrong>$99 once, forever\u003C/strong>\u003C/td>\u003C/tr>\u003C/tbody>\u003C/table>\n\u003Cp>FabForm.io gives you everything you need to launch high-converting forms — without locking you into a subscription.\u003C/p>\n\u003Ch2 id=\"built-for-people-who-just-want-it-to-work\">Built for People Who Just Want It to Work\u003C/h2>\n\u003Cp>You don’t need to be a developer. You don’t need to fiddle with code. FabForm.io is built for:\u003C/p>\n\u003Cul>\n\u003Cli>\u003Cstrong>Marketers\u003C/strong> running lead gen campaigns\u003C/li>\n\u003Cli>\u003Cstrong>Agencies\u003C/strong> building forms for clients\u003C/li>\n\u003Cli>\u003Cstrong>Small teams\u003C/strong> collecting feedback, signups, or surveys\u003C/li>\n\u003Cli>\u003Cstrong>Anyone\u003C/strong> who wants a clean, modern form without the monthly bill\u003C/li>\n\u003C/ul>\n\u003Ch2 id=\"no-subscriptions-no-upsells-just-99\">No Subscriptions. No Upsells. Just $99.\u003C/h2>\n\u003Cp>Typeform’s pricing starts at $25/month and climbs fast. FabForm.io keeps it simple:\u003C/p>\n\u003Cul>\n\u003Cli>\u003Cstrong>One-time payment of $99\u003C/strong>\u003C/li>\n\u003Cli>No recurring fees\u003C/li>\n\u003Cli>No usage limits\u003C/li>\n\u003Cli>No surprises\u003C/li>\n\u003C/ul>\n\u003Cp>You pay once. You own it. That’s it.\u003C/p>\n\u003Ch2 id=\"try-fabformio-today\">Try FabForm.io Today\u003C/h2>\n\u003Cp>If you’re ready to switch, FabForm.io makes it easy. Build your form, customize your branding, and go live in minutes — all for a flat $99.\u003C/p>\n\u003Cp>👉 \u003Ca href=\"https://fabform.io\">Start building with FabForm.io\u003C/a>\u003C/p>\n\u003Chr>",{"headings":181,"localImagePaths":200,"remoteImagePaths":201,"frontmatter":202,"imagePaths":206},[182,185,188,191,194,197],{"depth":99,"slug":183,"text":184},"fabformio-a-smarter-typeform-alternative-with-better-ux-and-no-recurring-costs","FabForm.io: A Smarter Typeform Alternative with Better UX and No Recurring Costs",{"depth":39,"slug":186,"text":187},"why-marketers-are-switching-to-fabformio","Why Marketers Are Switching to FabForm.io",{"depth":39,"slug":189,"text":190},"feature-comparison-fabformio-vs-typeform","Feature Comparison: FabForm.io vs Typeform",{"depth":39,"slug":192,"text":193},"built-for-people-who-just-want-it-to-work","Built for People Who Just Want It to Work",{"depth":39,"slug":195,"text":196},"no-subscriptions-no-upsells-just-99","No Subscriptions. No Upsells. Just $99.",{"depth":39,"slug":198,"text":199},"try-fabformio-today","Try FabForm.io Today",[],[],{"pubDate":203,"team":17,"title":81,"description":83,"image":204,"tags":205},["Date","2025-10-23T00:00:00.000Z"],{"url":92,"alt":86},[22,23,24,27,26,88],[],"typeform-alternative-fabform-99-dollar-one-time.md","typeform-too-expensive",{"id":208,"data":210,"body":222,"filePath":223,"assetImports":224,"digest":226,"rendered":227,"legacyId":283},{"title":211,"pubDate":212,"description":213,"team":17,"image":214,"tags":217},"Why Typeform’s Pricing Model Is So Expensive—and What You Can Use Instead",["Date","2025-10-25T00:00:00.000Z"],"Explore the hidden costs of Typeform’s pricing model—response limits, branding restrictions, and recurring fees—and discover how FabForm.io offers a scalable, one-time-payment alternative for marketers and growth teams.",{"url":215,"alt":216},"__ASTRO_IMAGE_/src/images/blog/typeform-is-too-expensive.jpg","Comparison of Typeform pricing tiers and FabForm benefits",[218,27,88,26,219,220,221],"Typeform pricing","unlimited responses","custom branding","one-time payment","## Introduction: The Hidden Cost of “Free” Forms\r\n\r\nTypeform is widely known for its sleek interface and conversational flow. It’s a popular choice for startups, marketers, and creators who want forms that feel modern and engaging. But once you move beyond the free plan, many teams discover that Typeform’s pricing model isn’t just expensive—it’s restrictive, unpredictable, and difficult to scale.\r\n\r\nIf you’ve ever searched for “Typeform alternatives with unlimited responses” or “how to remove Typeform branding,” you’re not alone. Thousands of users hit the same wall: they outgrow Typeform’s limits, but upgrading feels like paying more for less control.\r\n\r\n## The Real Pain Points Behind Typeform’s Pricing\r\n\r\n### Response Limits That Penalize Growth\r\n\r\nTypeform’s paid plans still cap the number of responses you can collect. For marketers running lead generation campaigns or product teams gathering feedback, this creates a paradox: the more successful your form is, the more you pay.\r\n\r\n- Free plan: 10 responses/month  \r\n- Basic plan: 100 responses/month  \r\n- Plus plan: 1,000 responses/month  \r\n\r\nIf you exceed these limits, you’re forced to upgrade—even if you don’t need additional features.\r\n\r\n### Essential Features Locked Behind Higher Tiers\r\n\r\nWant to remove Typeform’s branding? Add custom logic? Integrate with your CRM? You’ll need to pay more.\r\n\r\n- Custom branding: Only available on Plus and Business plans  \r\n- Logic jumps: Limited on lower tiers  \r\n- Integrations: Restricted unless you upgrade  \r\n\r\nThis tiered approach means you’re not paying for what you use—you’re paying to unlock what should be standard.\r\n\r\n### Recurring Costs That Add Up Fast\r\n\r\nTypeform’s monthly or annual billing model creates ongoing costs, even if your usage is seasonal or project-based. Agencies managing multiple clients often need separate workspaces, multiplying the expense.\r\n\r\n- Monthly billing: £25–£70+ per workspace  \r\n- Annual billing: Slight discount, but still recurring  \r\n- No one-time payment option  \r\n\r\nFor freelancers, small businesses, and growth teams, this pricing model quickly becomes unsustainable.\r\n\r\n### Limited Branding Control\r\n\r\nUnless you’re on a higher-tier plan, your forms carry Typeform’s logo. This undermines your brand and creates a disjointed experience for users.\r\n\r\n- No SVG logo support  \r\n- Limited header customization  \r\n- Typeform branding visible on lower plans  \r\n\r\nFor teams that care about design and brand consistency, this is a dealbreaker.\r\n\r\n### Workflow Complexity and Integration Friction\r\n\r\nTypeform’s logic jumps and integrations often feel clunky or limited. Connecting to external tools like Supabase, Airtable, or custom APIs requires workarounds or third-party services.\r\n\r\n- No native support for Supabase workflows  \r\n- Limited control over backend logic  \r\n- No built-in paid status tracking  \r\n\r\nThis forces developers and marketers to compromise on automation and data flow.\r\n\r\n## What Users Are Actually Searching For\r\n\r\nWhile they may not always say “I hate Typeform,” their search behavior tells the story. These are real-world phrases users type when they’re frustrated:\r\n\r\n- “Typeform too expensive for small business”  \r\n- “form builder with unlimited responses”  \r\n- “remove Typeform branding”  \r\n- “affordable Typeform alternative”  \r\n- “form builder with one-time payment”  \r\n- “Typeform response limit workaround”  \r\n- “form builder for client projects without per-seat pricing”  \r\n\r\nThese are high-intent queries from users actively looking for better options.\r\n\r\n## FabForm.io: Built to Solve These Exact Problems\r\n\r\nFabForm.io isn’t just another form builder—it’s a refined, scalable alternative designed for marketers, designers, and growth teams who care about clarity, control, and conversion.\r\n\r\n### One-Time Pricing\r\n\r\nNo subscriptions. No response limits. No surprise bills. Pay once, use forever.\r\n\r\n### Full Branding Control\r\n\r\nUpload your own SVG logo, customize headers, and remove all third-party branding.\r\n\r\n### Elegant UX and Conversion-Focused Design\r\n\r\nForms that look refined, load fast, and guide users smoothly to completion.\r\n\r\n### Idiomatic Supabase Workflows\r\n\r\nBuilt for developers who want clean, secure backend logic—especially for paid status tracking and user metadata.\r\n\r\n### SEO-Friendly Metadata\r\n\r\nEvery form is optimized for discoverability, with clean URLs and metadata that support organic growth.\r\n\r\n## Conclusion: Stop Paying to Scale\r\n\r\nTypeform’s pricing model isn’t broken—it’s just not built for teams who value control, clarity, and growth. If you’re tired of recurring fees, limited features, and branding restrictions, it’s time to switch.\r\n\r\nFabForm.io gives you the freedom to grow without penalty. Whether you’re running lead generation campaigns, onboarding users, or collecting feedback, FabForm lets you do it elegantly, affordably, and on your terms.\r\n\r\nTry FabForm.io today—the form builder that respects your brand, your budget, and your backend.\r\n\r\n---","src/content/posts/typeform-too-expensive.md",[225],"/src/images/blog/typeform-is-too-expensive.jpg","47edf3f8d1600405",{"html":228,"metadata":229},"\u003Ch2 id=\"introduction-the-hidden-cost-of-free-forms\">Introduction: The Hidden Cost of “Free” Forms\u003C/h2>\n\u003Cp>Typeform is widely known for its sleek interface and conversational flow. It’s a popular choice for startups, marketers, and creators who want forms that feel modern and engaging. But once you move beyond the free plan, many teams discover that Typeform’s pricing model isn’t just expensive—it’s restrictive, unpredictable, and difficult to scale.\u003C/p>\n\u003Cp>If you’ve ever searched for “Typeform alternatives with unlimited responses” or “how to remove Typeform branding,” you’re not alone. Thousands of users hit the same wall: they outgrow Typeform’s limits, but upgrading feels like paying more for less control.\u003C/p>\n\u003Ch2 id=\"the-real-pain-points-behind-typeforms-pricing\">The Real Pain Points Behind Typeform’s Pricing\u003C/h2>\n\u003Ch3 id=\"response-limits-that-penalize-growth\">Response Limits That Penalize Growth\u003C/h3>\n\u003Cp>Typeform’s paid plans still cap the number of responses you can collect. For marketers running lead generation campaigns or product teams gathering feedback, this creates a paradox: the more successful your form is, the more you pay.\u003C/p>\n\u003Cul>\n\u003Cli>Free plan: 10 responses/month\u003C/li>\n\u003Cli>Basic plan: 100 responses/month\u003C/li>\n\u003Cli>Plus plan: 1,000 responses/month\u003C/li>\n\u003C/ul>\n\u003Cp>If you exceed these limits, you’re forced to upgrade—even if you don’t need additional features.\u003C/p>\n\u003Ch3 id=\"essential-features-locked-behind-higher-tiers\">Essential Features Locked Behind Higher Tiers\u003C/h3>\n\u003Cp>Want to remove Typeform’s branding? Add custom logic? Integrate with your CRM? You’ll need to pay more.\u003C/p>\n\u003Cul>\n\u003Cli>Custom branding: Only available on Plus and Business plans\u003C/li>\n\u003Cli>Logic jumps: Limited on lower tiers\u003C/li>\n\u003Cli>Integrations: Restricted unless you upgrade\u003C/li>\n\u003C/ul>\n\u003Cp>This tiered approach means you’re not paying for what you use—you’re paying to unlock what should be standard.\u003C/p>\n\u003Ch3 id=\"recurring-costs-that-add-up-fast\">Recurring Costs That Add Up Fast\u003C/h3>\n\u003Cp>Typeform’s monthly or annual billing model creates ongoing costs, even if your usage is seasonal or project-based. Agencies managing multiple clients often need separate workspaces, multiplying the expense.\u003C/p>\n\u003Cul>\n\u003Cli>Monthly billing: £25–£70+ per workspace\u003C/li>\n\u003Cli>Annual billing: Slight discount, but still recurring\u003C/li>\n\u003Cli>No one-time payment option\u003C/li>\n\u003C/ul>\n\u003Cp>For freelancers, small businesses, and growth teams, this pricing model quickly becomes unsustainable.\u003C/p>\n\u003Ch3 id=\"limited-branding-control\">Limited Branding Control\u003C/h3>\n\u003Cp>Unless you’re on a higher-tier plan, your forms carry Typeform’s logo. This undermines your brand and creates a disjointed experience for users.\u003C/p>\n\u003Cul>\n\u003Cli>No SVG logo support\u003C/li>\n\u003Cli>Limited header customization\u003C/li>\n\u003Cli>Typeform branding visible on lower plans\u003C/li>\n\u003C/ul>\n\u003Cp>For teams that care about design and brand consistency, this is a dealbreaker.\u003C/p>\n\u003Ch3 id=\"workflow-complexity-and-integration-friction\">Workflow Complexity and Integration Friction\u003C/h3>\n\u003Cp>Typeform’s logic jumps and integrations often feel clunky or limited. Connecting to external tools like Supabase, Airtable, or custom APIs requires workarounds or third-party services.\u003C/p>\n\u003Cul>\n\u003Cli>No native support for Supabase workflows\u003C/li>\n\u003Cli>Limited control over backend logic\u003C/li>\n\u003Cli>No built-in paid status tracking\u003C/li>\n\u003C/ul>\n\u003Cp>This forces developers and marketers to compromise on automation and data flow.\u003C/p>\n\u003Ch2 id=\"what-users-are-actually-searching-for\">What Users Are Actually Searching For\u003C/h2>\n\u003Cp>While they may not always say “I hate Typeform,” their search behavior tells the story. These are real-world phrases users type when they’re frustrated:\u003C/p>\n\u003Cul>\n\u003Cli>“Typeform too expensive for small business”\u003C/li>\n\u003Cli>“form builder with unlimited responses”\u003C/li>\n\u003Cli>“remove Typeform branding”\u003C/li>\n\u003Cli>“affordable Typeform alternative”\u003C/li>\n\u003Cli>“form builder with one-time payment”\u003C/li>\n\u003Cli>“Typeform response limit workaround”\u003C/li>\n\u003Cli>“form builder for client projects without per-seat pricing”\u003C/li>\n\u003C/ul>\n\u003Cp>These are high-intent queries from users actively looking for better options.\u003C/p>\n\u003Ch2 id=\"fabformio-built-to-solve-these-exact-problems\">FabForm.io: Built to Solve These Exact Problems\u003C/h2>\n\u003Cp>FabForm.io isn’t just another form builder—it’s a refined, scalable alternative designed for marketers, designers, and growth teams who care about clarity, control, and conversion.\u003C/p>\n\u003Ch3 id=\"one-time-pricing\">One-Time Pricing\u003C/h3>\n\u003Cp>No subscriptions. No response limits. No surprise bills. Pay once, use forever.\u003C/p>\n\u003Ch3 id=\"full-branding-control\">Full Branding Control\u003C/h3>\n\u003Cp>Upload your own SVG logo, customize headers, and remove all third-party branding.\u003C/p>\n\u003Ch3 id=\"elegant-ux-and-conversion-focused-design\">Elegant UX and Conversion-Focused Design\u003C/h3>\n\u003Cp>Forms that look refined, load fast, and guide users smoothly to completion.\u003C/p>\n\u003Ch3 id=\"idiomatic-supabase-workflows\">Idiomatic Supabase Workflows\u003C/h3>\n\u003Cp>Built for developers who want clean, secure backend logic—especially for paid status tracking and user metadata.\u003C/p>\n\u003Ch3 id=\"seo-friendly-metadata\">SEO-Friendly Metadata\u003C/h3>\n\u003Cp>Every form is optimized for discoverability, with clean URLs and metadata that support organic growth.\u003C/p>\n\u003Ch2 id=\"conclusion-stop-paying-to-scale\">Conclusion: Stop Paying to Scale\u003C/h2>\n\u003Cp>Typeform’s pricing model isn’t broken—it’s just not built for teams who value control, clarity, and growth. If you’re tired of recurring fees, limited features, and branding restrictions, it’s time to switch.\u003C/p>\n\u003Cp>FabForm.io gives you the freedom to grow without penalty. Whether you’re running lead generation campaigns, onboarding users, or collecting feedback, FabForm lets you do it elegantly, affordably, and on your terms.\u003C/p>\n\u003Cp>Try FabForm.io today—the form builder that respects your brand, your budget, and your backend.\u003C/p>\n\u003Chr>",{"headings":230,"localImagePaths":276,"remoteImagePaths":277,"frontmatter":278,"imagePaths":282},[231,234,237,240,243,246,249,252,255,258,261,264,267,270,273],{"depth":39,"slug":232,"text":233},"introduction-the-hidden-cost-of-free-forms","Introduction: The Hidden Cost of “Free” Forms",{"depth":39,"slug":235,"text":236},"the-real-pain-points-behind-typeforms-pricing","The Real Pain Points Behind Typeform’s Pricing",{"depth":43,"slug":238,"text":239},"response-limits-that-penalize-growth","Response Limits That Penalize Growth",{"depth":43,"slug":241,"text":242},"essential-features-locked-behind-higher-tiers","Essential Features Locked Behind Higher Tiers",{"depth":43,"slug":244,"text":245},"recurring-costs-that-add-up-fast","Recurring Costs That Add Up Fast",{"depth":43,"slug":247,"text":248},"limited-branding-control","Limited Branding Control",{"depth":43,"slug":250,"text":251},"workflow-complexity-and-integration-friction","Workflow Complexity and Integration Friction",{"depth":39,"slug":253,"text":254},"what-users-are-actually-searching-for","What Users Are Actually Searching For",{"depth":39,"slug":256,"text":257},"fabformio-built-to-solve-these-exact-problems","FabForm.io: Built to Solve These Exact Problems",{"depth":43,"slug":259,"text":260},"one-time-pricing","One-Time Pricing",{"depth":43,"slug":262,"text":263},"full-branding-control","Full Branding Control",{"depth":43,"slug":265,"text":266},"elegant-ux-and-conversion-focused-design","Elegant UX and Conversion-Focused Design",{"depth":43,"slug":268,"text":269},"idiomatic-supabase-workflows","Idiomatic Supabase Workflows",{"depth":43,"slug":271,"text":272},"seo-friendly-metadata","SEO-Friendly Metadata",{"depth":39,"slug":274,"text":275},"conclusion-stop-paying-to-scale","Conclusion: Stop Paying to Scale",[],[],{"pubDate":279,"team":17,"title":211,"description":213,"image":280,"tags":281},["Date","2025-10-25T00:00:00.000Z"],{"url":225,"alt":216},[218,27,88,26,219,220,221],[],"typeform-too-expensive.md"]